batch_image_processing/__init__.py
batch_image_processing/image_processor.py
batch_image_processing-0.1.5.dist-info/LICENSE.md
batch_image_processing-0.1.5.dist-info/METADATA
batch_image_processing-0.1.5.dist-info/WHEEL
batch_image_processing-0.1.5.dist-info/RECORD
